mypk1/__init__.py
mypk1/example.py
mypk1-0.0.6.dist-info/LICENSE
mypk1-0.0.6.dist-info/METADATA
mypk1-0.0.6.dist-info/WHEEL
mypk1-0.0.6.dist-info/entry_points.txt
mypk1-0.0.6.dist-info/top_level.txt
mypk1-0.0.6.dist-info/RECORD
