Metadata-Version: 2.1
Name: mypk1
Version: 0.0.6
Summary: A small example package
Home-page: https://github.com/pypa/sampleproject
Author: yangzhi
Author-email: y.zhisky@163.com
License: UNKNOWN
Project-URL: Bug Tracker, https://github.com/pypa/sampleproject/issues
Platform: UNKNOWN
Classifier: Programming Language :: Python :: 3
Classifier: License :: OSI Approved :: MIT License
Classifier: Operating System :: OS Independent
Requires-Python: >=3.6
License-File: LICENSE
